{
  "project_info": {
    "project_number": "262873822666",
    "project_id": "tesshile",
    "storage_bucket": "tesshile.appspot.com"
  },
  "client": [
    {
      "client_info": {
        "mobilesdk_app_id": "1:262873822666:android:1fca5fa9b8b1934f57cb33",
        "android_client_info": {
          "package_name": "com.consrimcasa_mobile_app.tesshile"
        }
      },
      "oauth_client": [],
      "api_key": [
        {
          "current_key": "AIzaSyCFlfm526dXR8e7NCM3JDppe9DsOHGpJ4M"
        }
      ],
      "services": {
        "appinvite_service": {
          "other_platform_oauth_client": []
        }
      }
    }
  ],
  "configuration_version": "1"
}